{
  "schema_version": "0.2.7",
  "record_metadata": {
    "uuid": "583ab46e-ccb8-4a49-9912-7771683cd605",
    "record_created_on": "2021-11-01",
    "record_created_by": "Kudela, Xenia Monika",
    "last_edited_on": "2025-03-20",
    "interviewed": true
  },
  "project": {
    "title": "MAJLIS. The Transformation of Jewish Literature in Arabic in the Islamicate World",
    "abbr": "MAJLIS",
    "type": "project",
    "ref": [],
    "date": [
      {
        "from": "2021",
        "to": "2026"
      }
    ],
    "maintained": true,
    "websites": [
      "https://www.naher-osten.uni-muenchen.de/forschung/majlis/index.html",
      "https://github.com/majlis-erc",
      "https://malisprojekte.web.th-koeln.de/wordpress/manuforma-katalogisierung-von-handschriften-im-browser/"
    ],
    "project_desc": "This project is dedicated to the hitherto under-researched Judaeo-Arabic literature from the period between the 9th and the 11th century. The overall aim is to explore how the adoption of Arabic language and Arabic intellectual tradition influenced the Jewish literary creativity in this period. The project will proceed by applying state-of-the-art digital tools to analyze manuscripts, trace changes in the Jewish literature, identify the dominant scholars and to compare the Judaeo-Arabic literature with non-Jewish literary traditions of the time.",
    "places": [
      {
        "place_name": {
          "text": "Munich",
          "ref": [
            "https://www.geonames.org/2867714/munich.html"
          ]
        },
        "coordinates": {
          "lat": "48.13743",
          "lng": "11.57549"
        }
      }
    ],
    "lang": [
      "eng"
    ],
    "related_institutions": [
      {
        "relation_type": "host",
        "org_name": {
          "text": "Ludwig-Maximilians-Universität Munich",
          "ref": [
            "https://www.wikidata.org/wiki/Q156598",
            "https://ror.org/05591te55"
          ]
        },
        "websites": [
          "https://www.lmu.de/de/index.html"
        ]
      }
    ],
    "related_entities": [
      {
        "relation_type": "sibling",
        "title": "The Hebrew Palaeography Album",
        "uuid": "80ba021c-7f2e-421a-b897-71c3eadcca11"
      },
      {
        "relation_type": "sibling",
        "title": "MAJLIS. The Transformation of Jewish Literature in Arabic in the Islamicate World",
        "uuid": "583ab46e-ccb8-4a49-9912-7771683cd605"
      },
      {
        "relation_type": "cooperation",
        "title": "eScriptorium",
        "uuid": "31ad93ff-ca97-4cf0-b30c-60685624e2c8"
      },
      {
        "relation_type": "cooperation",
        "title": "Union Catalogue of Manuscripts from the Islamicate World",
        "uuid": "9734b5c3-fa35-4e45-878e-1deb62db97d5"
      },
      {
        "relation_type": "cooperation",
        "title": "Beta maṣāḥǝft Manuscripts of Ethiopia and Eritrea",
        "uuid": "169677fd-14f9-46e7-b8f1-2202fb91397c"
      }
    ],
    "people": [
      {
        "pers_name": {
          "text": "Vollandt, Ronny",
          "ref": [
            "https://orcid.org/0000-0003-3701-9429",
            "https://d-nb.info/gnd/1173742050"
          ]
        },
        "roles": [
          "supervision"
        ],
        "websites": [
          "https://www.naher-osten.uni-muenchen.de/personen/professoren/ronny_vollandt/index.html"
        ]
      }
    ],
    "research_data": {
      "lang": [
        "ara"
      ],
      "sustainability_plan": {
        "project_website": 1.0,
        "Github": 1.0,
        "data_accessibility": 1.0,
        "webhosting": 0.5,
        "publications": 0.0,
        "publication_count": 0,
        "open_access_count": 0
      },
      "publications": {
        "open_access": 100,
        "licensing": [
          "CC BY-NC 4.0"
        ]
      },
      "data": {
        "datatypes": [
          {
            "label": "XML",
            "stage": "final",
            "licensing": [
              "CC BY-NC 4.0"
            ],
            "open_access": 100
          }
        ],
        "repositories": [
          {
            "label": "GitHub",
            "accessibility": "public",
            "ref": [],
            "websites": [
              "https://github.com/majlis-erc"
            ],
            "licensing": [
              "CC BY-NC 4.0"
            ],
            "description": ""
          },
          {
            "label": "Open Data LMU",
            "accessibility": "public",
            "ref": [],
            "websites": [
              "https://data.ub.uni-muenchen.de/"
            ],
            "licensing": [
              "CC BY-NC 4.0"
            ],
            "description": "There is no instance yet; the project will be migrated in the future"
          }
        ]
      }
    },
    "stack": {
      "database": [
        "XML"
      ],
      "backend": [
        "manuForma",
        "XSLT",
        "XForm",
        "XQuery",
        "eXist-db"
      ],
      "frontend": [
        "Srophe",
        "JS",
        "XSLT",
        "XHTML"
      ],
      "tools": [
        {
          "label": "manuForma",
          "self_developed": true,
          "ref": [],
          "websites": [
            "https://github.com/majlis-erc/manuForma"
          ],
          "description": "TEI-XML File Generator"
        },
        {
          "label": "Srophe",
          "self_developed": false,
          "ref": [],
          "websites": [
            "https://srophe.app/"
          ],
          "description": "Frontend framework for projects working with TEI-XML"
        }
      ],
      "languages": [
        "XQuery",
        "XSLT",
        "JS",
        "XHTML",
        "CSS"
      ]
    },
    "policies": [
      {
        "description": "",
        "ref": []
      }
    ],
    "keywords": [
      "arabic_studies",
      "literary_studies",
      "digital_preservation",
      "jewish_studies",
      "catalog"
    ],
    "category": "digital_preservation",
    "comment": "All publications, data, and code created during the course of the project are available in open access,"
  }
}